poromics/__init__.py
poromics/_metrics.py
poromics/cli.py
poromics/julia_helpers.py
poromics/juliapkg.json
poromics/py.typed
poromics/settings.py
poromics/utils.py
poromics/version.py
poromics/conf/__init__.py
poromics/conf/settings.py
poromics-0.0.7.dist-info/METADATA
poromics-0.0.7.dist-info/WHEEL
poromics-0.0.7.dist-info/entry_points.txt
poromics-0.0.7.dist-info/licenses/LICENSE
poromics-0.0.7.dist-info/RECORD
