Metadata-Version: 2.4
Name: poromics
Version: 0.0.7
Summary: A tool for rapid estimation of transport properties of 3D images of porous materials
Author-email: Amin Sadeghi <amin.sadeghi@live.com>
Maintainer-email: Amin Sadeghi <amin.sadeghi@live.com>
License: MIT License
License-File: LICENSE
Requires-Python: <3.13,>=3.10
Requires-Dist: ipykernel>=6.29.5
Requires-Dist: ipython>=8.34.0
Requires-Dist: juliacall>=0.9.24
Requires-Dist: juliapkg>=0.1.16
Requires-Dist: loguru>=0.7.3
Requires-Dist: numba>=0.59.0
Requires-Dist: numpy>=2.1.3
Requires-Dist: porespy>=2.4.2
Requires-Dist: pydantic-settings
Requires-Dist: pydantic~=2.0
Requires-Dist: tqdm>=4.67.1
Requires-Dist: typer
